{"working_dir":null,"default_chunk_options":{"echo":true},"chunk_definitions":[{"row":9,"row_count":1,"visible":true,"expansion_state":0,"options":{"engine":"r","label":"setup","include":false,"dev":"png"},"document_id":"A5A30936","chunk_id":"csetup_chunk","chunk_label":"setup"},{"row":26,"row_count":1,"visible":true,"expansion_state":0,"options":{"engine":"r","label":"unnamed-chunk-1","dev":"png"},"document_id":"A5A30936","chunk_id":"cgrwh8375obi1","chunk_label":"unnamed-chunk-1"},{"row":34,"row_count":1,"visible":true,"expansion_state":0,"options":{"engine":"r","label":"unnamed-chunk-2","dev":"png"},"document_id":"A5A30936","chunk_id":"c14k5fr9r9v8v","chunk_label":"unnamed-chunk-2"},{"row":40,"row_count":1,"visible":true,"expansion_state":0,"options":{"engine":"r","label":"unnamed-chunk-3","dev":"png"},"document_id":"A5A30936","chunk_id":"cbt2mponx63cz","chunk_label":"unnamed-chunk-3"},{"row":46,"row_count":1,"visible":true,"expansion_state":0,"options":{"engine":"r","label":"unnamed-chunk-4","dev":"png"},"document_id":"A5A30936","chunk_id":"c9cogphgag26l","chunk_label":"unnamed-chunk-4"},{"row":61,"row_count":1,"visible":true,"expansion_state":0,"options":{"engine":"r","label":"unnamed-chunk-5","dev":"png"},"document_id":"A5A30936","chunk_id":"cl4xrf4roc3kp","chunk_label":"unnamed-chunk-5"},{"row":73,"row_count":1,"visible":true,"expansion_state":0,"options":{"engine":"r","label":"unnamed-chunk-6","dev":"png"},"document_id":"A5A30936","chunk_id":"cpiscsjf25ioz","chunk_label":"unnamed-chunk-6"}],"doc_write_time":1707969420}