{"chunk_definitions":[{"chunk_id":"caozy8lo6qj57","expansion_state":0,"options":[],"row":23,"row_count":1,"visible":true},{"chunk_id":"c1o4a3t0sksv4","expansion_state":0,"options":[],"row":35,"row_count":1,"visible":true},{"chunk_id":"c6vvuxcrf4d0w","expansion_state":0,"options":[],"row":55,"row_count":1,"visible":true},{"chunk_id":"csvfvufb730gl","expansion_state":0,"options":[],"row":79,"row_count":1,"visible":true},{"chunk_id":"cbvwfj3si1oqk","expansion_state":0,"options":[],"row":95,"row_count":1,"visible":true}],"doc_write_time":1707692095.23942}
